d8s_utility/__init__.py
d8s_utility/utility.py
d8s_utility/utility_temp_utils.py
tests/__init__.py
tests/test_utility.py
d8s_utility-0.8.0.dist-info/COPYING
d8s_utility-0.8.0.dist-info/COPYING.LESSER
d8s_utility-0.8.0.dist-info/METADATA
d8s_utility-0.8.0.dist-info/WHEEL
d8s_utility-0.8.0.dist-info/top_level.txt
d8s_utility-0.8.0.dist-info/zip-safe
d8s_utility-0.8.0.dist-info/RECORD
