Metadata-Version: 2.1
Name: d8s-utility
Version: 0.8.0
Summary: Democritus functions for working with utility functions.
Home-page: https://github.com/democritus-project/d8s-utility
Author: Floyd Hightower
Author-email: floyd.hightower27@gmail.com
License: GNU Lesser General Public License v3
Keywords: democritus,utility,python,utility-functions,utility-functions-utility,utilities,utils
Platform: UNKNOWN
Classifier: Development Status :: 2 - Pre-Alpha
Classifier: Intended Audience :: Developers
Classifier: License :: OSI Approved :: GNU Lesser General Public License v3 or later (LGPLv3+)
Classifier: Natural Language :: English
Classifier: Programming Language :: Python :: 3
Classifier: Programming Language :: Python :: 3.4
Classifier: Programming Language :: Python :: 3.5
Classifier: Programming Language :: Python :: 3.6
Classifier: Programming Language :: Python :: 3.7
Classifier: Programming Language :: Python :: 3.8
Classifier: Programming Language :: Python :: 3.9
Requires-Dist: d8s-file-system (<1.0.0)
Requires-Dist: d8s-networking (==0.*)
Requires-Dist: d8s-urls (==0.*)
Requires-Dist: d8s-lists (==0.*)
Requires-Dist: importlib-metadata ; python_version < "3.8"
